colibripy/__init__.py
colibripy/stats/__init__.py
colibripy/stats/parametric/__init__.py
colibripy/stats/parametric/t_test.py
colibripy/tests/__init__.py
colibripy/tests/tests_stats_parameteric_t_test/__init__.py
colibripy/tests/tests_stats_parameteric_t_test/test_t_test.py
colibripy-1.0.0.dist-info/METADATA
colibripy-1.0.0.dist-info/WHEEL
colibripy-1.0.0.dist-info/RECORD
