Metadata-Version: 2.1
Name: colibripy
Version: 1.0.0
Summary: The package contains statsitical tests such as one-sample, two-sample and paired t-test. Residual analysis and plotting are also supported.
Home-page: https://github.com/MMateo1120/colibripy
License: MIT
Keywords: statistics,parametric tests,t-test,one-sample t-test,two-sample t-test,paired t-test
Author: MMateo1120
Author-email: mmateo1120@gmail.com
Requires-Python: >=3.12,<4.0
Classifier: Intended Audience :: Science/Research
Classifier: License :: OSI Approved :: MIT License
Classifier: Operating System :: Microsoft :: Windows
Classifier: Programming Language :: Python
Classifier: Programming Language :: Python :: 3
Classifier: Programming Language :: Python :: 3.12
Classifier: Topic :: Scientific/Engineering
Requires-Dist: matplotlib (==3.9.1)
Requires-Dist: numpy (==2.0.1)
Requires-Dist: pandas (==2.2.2)
Requires-Dist: pytest (==8.3.2)
Requires-Dist: scikit-learn (==1.5.1)
Requires-Dist: scipy (==1.14.0)
Requires-Dist: seaborn (==0.13.2)
Requires-Dist: statsmodels (==0.14.2)
Requires-Dist: tabulate (==0.9.0)
Project-URL: Repository, https://github.com/MMateo1120/colibripy
